.gitignore
.travis.yml
CHANGES.txt
LICENSE.txt
MANIFEST.in
README.rst
bootstrap.py
buildout.cfg
setup.py
versions.cfg
src/mongopersist/README.txt
src/mongopersist/__init__.py
src/mongopersist/conflict.py
src/mongopersist/datamanager.py
src/mongopersist/interfaces.py
src/mongopersist/mapping.py
src/mongopersist/optimistic-data-dumping.txt
src/mongopersist/performance.py
src/mongopersist/pool.py
src/mongopersist/pymongo.py
src/mongopersist/serialize.py
src/mongopersist/serializers.py
src/mongopersist/testing.py
src/mongopersist.egg-info/PKG-INFO
src/mongopersist.egg-info/SOURCES.txt
src/mongopersist.egg-info/dependency_links.txt
src/mongopersist.egg-info/entry_points.txt
src/mongopersist.egg-info/not-zip-safe
src/mongopersist.egg-info/requires.txt
src/mongopersist.egg-info/top_level.txt
src/mongopersist/tests/__init__.py
src/mongopersist/tests/test_conflict.py
src/mongopersist/tests/test_datamanager.py
src/mongopersist/tests/test_doc.py
src/mongopersist/tests/test_mapping.py
src/mongopersist/tests/test_serialize.py
src/mongopersist/zope/__init__.py
src/mongopersist/zope/annotation.py
src/mongopersist/zope/container.py
src/mongopersist/zope/dublincore.py
src/mongopersist/zope/interfaces.py
src/mongopersist/zope/schema.py
src/mongopersist/zope/tests/__init__.py
src/mongopersist/zope/tests/test_container.py