Metadata-Version: 1.1
Name: mongopersist
Version: 0.8.4
Summary: Mongo Persistence Backend
Home-page: https://github.com/zopefoundation/mongopersist
Author: Stephan Richter
Author-email: stephan.richter@gmail.com
License: ZPL 2.1
Keywords: mongo persistent
Platform: UNKNOWN
Classifier: Development Status :: 4 - Beta
Classifier: Intended Audience :: Developers
Classifier: Programming Language :: Python
Classifier: Programming Language :: Python :: 2
Classifier: Programming Language :: Python :: 2.7
Classifier: Framework :: ZODB
Classifier: License :: OSI Approved :: Zope Public License
Classifier: Natural Language :: English
Classifier: Operating System :: OS Independent
